intel_seed/__init__.py
intel_seed/intel_seed.py
intel_seed/librdseed.dll
intel_seed/librdseed.so
intel_seed/rdseed_bytes.c
intelseed-1.1.0.dist-info/licenses/LICENSE
intelseed-1.1.0.dist-info/METADATA
intelseed-1.1.0.dist-info/WHEEL
intelseed-1.1.0.dist-info/top_level.txt
intelseed-1.1.0.dist-info/RECORD
