Metadata-Version: 2.4
Name: intelseed
Version: 1.1.0
Summary: A Python module for Intel RDSEED hardware random number generation.
Author: Thiago Jung
Author-email: Thiago Jung <tjm.plastica@gmail.com>
License-Expression: MIT
Project-URL: Homepage, https://github.com/Thiagojm/IntelSeed
Project-URL: Issues, https://github.com/Thiagojm/IntelSeed/issues
Classifier: Development Status :: 4 - Beta
Classifier: Intended Audience :: Developers
Classifier: Programming Language :: Python :: 3
Classifier: Programming Language :: Python :: 3.8
Classifier: Programming Language :: Python :: 3.9
Classifier: Programming Language :: Python :: 3.10
Classifier: Programming Language :: Python :: 3.11
Classifier: Programming Language :: Python :: 3.12
Classifier: Programming Language :: Python :: 3.13
Classifier: Topic :: Security :: Cryptography
Classifier: Topic :: Software Development :: Libraries :: Python Modules
Classifier: Operating System :: POSIX :: Linux
Classifier: Operating System :: Microsoft :: Windows
Requires-Python: >=3.8
License-File: LICENSE
Provides-Extra: dev
Requires-Dist: pytest; extra == "dev"
Requires-Dist: black; extra == "dev"
Requires-Dist: flake8; extra == "dev"
Dynamic: author
Dynamic: license-file
Dynamic: requires-python
